Dajax-1.3.dist-info/DESCRIPTION.rst
Dajax-1.3.dist-info/METADATA
Dajax-1.3.dist-info/RECORD
Dajax-1.3.dist-info/WHEEL
Dajax-1.3.dist-info/metadata.json
Dajax-1.3.dist-info/top_level.txt
dajax/__init__.py
dajax/apps.py
dajax/urls.py
dajax/views.py
dajax/static/dajax/js/jquery.dajax.js
